{
  "ret": 1,
  "msg": "success",
  "data": {
    "links": [
      {
        "title": "有道首页",
        "link": "http://dict.youdao.com/"
      },
      {
        "title": "Markdown to HTML",
        "link": "http://www.mazey.net/app/markdown/"
      },
      {
        "title": "百度地图",
        "link": "https://map.baidu.com/"
      },
      {
        "title": "Babel",
        "link": "https://www.babeljs.cn/repl/"
      },
      {
        "title": "QQ邮箱",
        "link": "https://mail.qq.com"
      },
      {
        "title": "Unicode编码转换",
        "link": "http://tool.chinaz.com/Tools/Unicode.aspx"
      }
    ]
  }
}
